XiabanDanglaoban/README.md
XiabanDanglaoban/__init__.py
XiabanDanglaoban/__main__.py
XiabanDanglaoban/file.epub
XiabanDanglaoban/index.html
XiabanDanglaoban/css/__init__.py
XiabanDanglaoban/css/annotations.css
XiabanDanglaoban/css/main.css
XiabanDanglaoban/css/normalize.css
XiabanDanglaoban/css/popup.css
XiabanDanglaoban/font/__init__.py
XiabanDanglaoban/font/fontello.eot
XiabanDanglaoban/font/fontello.svg
XiabanDanglaoban/font/fontello.ttf
XiabanDanglaoban/font/fontello.woff
XiabanDanglaoban/img/__init__.py
XiabanDanglaoban/img/annotator-glyph-sprite.png
XiabanDanglaoban/img/annotator-icon-sprite.png
XiabanDanglaoban/img/apple-touch-icon.png
XiabanDanglaoban/img/cancelfullscreen.png
XiabanDanglaoban/img/close.png
XiabanDanglaoban/img/fullscreen.png
XiabanDanglaoban/img/loader.gif
XiabanDanglaoban/img/menu-icon.png
XiabanDanglaoban/img/save.png
XiabanDanglaoban/img/saved.png
XiabanDanglaoban/img/settings-s.png
XiabanDanglaoban/img/settings.png
XiabanDanglaoban/img/star.png
XiabanDanglaoban/js/__init__.py
XiabanDanglaoban/js/epub.js
XiabanDanglaoban/js/epub.min.js
XiabanDanglaoban/js/epub.min.map
XiabanDanglaoban/js/hooks.min.js
XiabanDanglaoban/js/hooks.min.map
XiabanDanglaoban/js/reader.js
XiabanDanglaoban/js/reader.js.map
XiabanDanglaoban/js/reader.min.js
XiabanDanglaoban/js/reader.min.map
XiabanDanglaoban/js/hooks/__init__.py
XiabanDanglaoban/js/hooks/extensions/__init__.py
XiabanDanglaoban/js/hooks/extensions/highlight.js
XiabanDanglaoban/js/libs/__init__.py
XiabanDanglaoban/js/libs/jquery.min.js
XiabanDanglaoban/js/libs/localforage.min.js
XiabanDanglaoban/js/libs/screenfull.js
XiabanDanglaoban/js/libs/screenfull.min.js
XiabanDanglaoban/js/libs/zip.min.js
XiabanDanglaoban/js/plugins/__init__.py
XiabanDanglaoban/js/plugins/hypothesis.js
XiabanDanglaoban/js/plugins/search.js
xiaban_danglaoban-2022.10.15.0.dist-info/METADATA
xiaban_danglaoban-2022.10.15.0.dist-info/WHEEL
xiaban_danglaoban-2022.10.15.0.dist-info/entry_points.txt
xiaban_danglaoban-2022.10.15.0.dist-info/top_level.txt
xiaban_danglaoban-2022.10.15.0.dist-info/RECORD
